CHANGES.txt
buildout.cfg
setup.py
src/z3c/__init__.py
src/z3c.dav.egg-info/PKG-INFO
src/z3c.dav.egg-info/SOURCES.txt
src/z3c.dav.egg-info/dependency_links.txt
src/z3c.dav.egg-info/namespace_packages.txt
src/z3c.dav.egg-info/not-zip-safe
src/z3c.dav.egg-info/requires.txt
src/z3c.dav.egg-info/top_level.txt
src/z3c/dav/README.txt
src/z3c/dav/TODO.txt
src/z3c/dav/__init__.py
src/z3c/dav/adapters.py
src/z3c/dav/configure.zcml
src/z3c/dav/copymove.py
src/z3c/dav/coreproperties.py
src/z3c/dav/datamodel.txt
src/z3c/dav/ftesting.zcml
src/z3c/dav/ifvalidator.py
src/z3c/dav/interfaces.py
src/z3c/dav/locking.py
src/z3c/dav/locking.txt
src/z3c/dav/mkcol.py
src/z3c/dav/properties.py
src/z3c/dav/propfind.py
src/z3c/dav/proppatch.py
src/z3c/dav/publisher.py
src/z3c/dav/testing.py
src/z3c/dav/utils.py
src/z3c/dav/widgets.py
src/z3c/dav/exceptions/__init__.py
src/z3c/dav/exceptions/badrequest.pt
src/z3c/dav/exceptions/browser.py
src/z3c/dav/exceptions/configure.zcml
src/z3c/dav/exceptions/ftests/__init__.py
src/z3c/dav/exceptions/ftests/test_baseexceptions.py
src/z3c/dav/exceptions/tests/__init__.py
src/z3c/dav/exceptions/tests/test_multiviews.py
src/z3c/dav/exceptions/tests/test_simpleviews.py
src/z3c/dav/ftests/__init__.py
src/z3c/dav/ftests/dav.py
src/z3c/dav/ftests/ftesting.zcml
src/z3c/dav/ftests/test_copymove.py
src/z3c/dav/ftests/test_docs.py
src/z3c/dav/ftests/test_mkcol.py
src/z3c/dav/ftests/test_propfind.py
src/z3c/dav/ftests/test_proppatch.py
src/z3c/dav/ftests/zopefolder.txt
src/z3c/dav/tests/__init__.py
src/z3c/dav/tests/test_copymove.py
src/z3c/dav/tests/test_doctests.py
src/z3c/dav/tests/test_inputwidgets.py
src/z3c/dav/tests/test_propfind.py
src/z3c/dav/tests/test_proppatch.py
src/z3c/dav/tests/test_publisher.py
src/z3c/dav/tests/test_widgets.py