Metadata-Version: 1.0
Name: z3c.dav
Version: 1.0b2
Summary: Implementation of the WebDAV protocol for Zope3
Home-page: http://launchpad.net/z3c.dav
Author: Michael Kerrin
Author-email: michael.kerrin@openapp.ie
License: ZPL
Platform: UNKNOWN
Classifier: Environment :: Web Environment
Classifier: Intended Audience :: Developers
Classifier: License :: OSI Approved :: Zope Public License
Classifier: Programming Language :: Python
Classifier: Framework :: Zope3
